setup.py
src/gitology/__init__.py
src/gitology/blog.py
src/gitology/config.py
src/gitology/document.py
src/gitology/gitter.py
src/gitology/odict.py
src/gitology/path.py
src/gitology/tests.py
src/gitology/utils.py
src/gitology.egg-info/PKG-INFO
src/gitology.egg-info/SOURCES.txt
src/gitology.egg-info/dependency_links.txt
src/gitology.egg-info/top_level.txt
src/gitology/d/__init__.py
src/gitology/d/forms.py
src/gitology/d/librecaptcha.py
src/gitology/d/middleware.py
src/gitology/d/models.py
src/gitology/d/recaptcha_forms.py
src/gitology/d/themed_template_loader.py
src/gitology/d/urls.py
src/gitology/d/utils.py
src/gitology/d/views.py
src/gitology/d/templatetags/__init__.py
src/gitology/d/templatetags/clevercsstag.py
src/gitology/d/templatetags/documents.py
src/gitology/d/templatetags/enable_comments.py
src/gitology/d/templatetags/lookup.py
src/gitology/d/templatetags/paginator.py
src/tools/gitology-blog-document
src/tools/gitology-blog-start
src/tools/gitology-info
src/tools/gitology-init
src/tools/gitology-wiki-document