Metadata-Version: 1.0
Name: gitology
Version: 0.0.1
Summary: Git based blog/wiki system using DJango
Home-page: http://code.google.com/p/gitology/
Author: Amit Upadhyay
Author-email: gitology@amitu.com
License: BSD
Keywords: git django blog wiki
Platform: UNKNOWN
